{
  "created_at": "2026-05-04T10:25:45.412922+00:00",
  "random_state": 42,
  "model_type": "TFIDF word/char ngrams + KNeighbors regressor + KNeighbors classifier",
  "activity_profile_columns": [
    "activity_movement",
    "activity_energy",
    "activity_positivity",
    "activity_focus",
    "activity_calm",
    "activity_acoustic"
  ],
  "activity_prototypes": {
    "desahogo_emocional": [
      0.0,
      0.05,
      0.05,
      0.3,
      0.95,
      0.85
    ],
    "entrenamiento_intenso": [
      0.95,
      0.95,
      0.65,
      0.45,
      0.1,
      0.15
    ],
    "correr": [
      1.0,
      0.95,
      0.7,
      0.35,
      0.05,
      0.1
    ],
    "baile_fiesta": [
      0.95,
      0.9,
      0.95,
      0.2,
      0.05,
      0.05
    ],
    "limpieza_domestica": [
      0.75,
      0.7,
      0.55,
      0.35,
      0.15,
      0.2
    ],
    "estudio_trabajo": [
      0.15,
      0.25,
      0.45,
      0.95,
      0.7,
      0.75
    ],
    "alimentacion": [
      0.1,
      0.2,
      0.55,
      0.5,
      0.65,
      0.55
    ],
    "relajacion": [
      0.05,
      0.15,
      0.55,
      0.55,
      0.95,
      0.85
    ],
    "dormir": [
      0.0,
      0.05,
      0.35,
      0.6,
      1.0,
      0.95
    ],
    "caminar_paseo": [
      0.45,
      0.45,
      0.65,
      0.45,
      0.5,
      0.45
    ],
    "conducir_viaje": [
      0.45,
      0.6,
      0.75,
      0.45,
      0.35,
      0.25
    ],
    "actividad_general": [
      0.45,
      0.5,
      0.55,
      0.45,
      0.35,
      0.3
    ]
  },
  "training_examples": 1368,
  "note": "Este modelo combina un interprete linguistico con reglas por palabras clave. Convierte texto libre en dimensiones musicales como energia, movimiento, foco y calma."
}